pypz/deployers/k8s.py
pypz/operators/k8s.py
pypz_k8s_deployer-0.9.5.dist-info/licenses/LICENSE
pypz_k8s_deployer-0.9.5.dist-info/METADATA
pypz_k8s_deployer-0.9.5.dist-info/WHEEL
pypz_k8s_deployer-0.9.5.dist-info/top_level.txt
pypz_k8s_deployer-0.9.5.dist-info/RECORD
