Metadata-Version: 2.4
Name: pypz-k8s-deployer
Version: 0.9.5
Summary: This package provides the Kubernetes implementation of the deployer interface for pypz.
Author-email: Laszlo Anka <laszlo.anka@gmail.com>
License: Apache-2.0
Project-URL: Documentation, https://pypz.dev
Project-URL: Repository, https://github.com/lazlowa/pypz-python
Keywords: pypz,k8s,kubernetes,deployer
Classifier: Natural Language :: English
Classifier: Operating System :: OS Independent
Classifier: Programming Language :: Python :: 3.11
Requires-Python: >=3.11
License-File: LICENSE
Requires-Dist: pypz-core
Requires-Dist: kubernetes==v28.1.0
Requires-Dist: certifi~=2023.11.17
Provides-Extra: static
Requires-Dist: flake8~=7.0.0; extra == "static"
Requires-Dist: flake8-html~=0.4.3; extra == "static"
Requires-Dist: mypy~=1.8.0; extra == "static"
Requires-Dist: coverage~=7.4.1; extra == "static"
Dynamic: license-file
